square_database_helper/__init__.py
square_database_helper/main.py
square_database_helper/pydantic_models.py
square_database_helper-2.7.1.dist-info/WHEEL
square_database_helper-2.7.1.dist-info/METADATA
square_database_helper-2.7.1.dist-info/RECORD
