Metadata-Version: 2.3
Name: square_database_helper
Version: 2.7.1
Summary: helper to access the database layer for my personal server.
Keywords: database,helper,utilities
Author: Parth Mukesh Mangtani
Author-email: Parth Mukesh Mangtani <thepmsquare@gmail.com>
License: GPLv3
Classifier: Development Status :: 3 - Alpha
Classifier: Intended Audience :: Developers
Classifier: License :: OSI Approved :: GNU General Public License v3 (GPLv3)
Classifier: Operating System :: OS Independent
Classifier: Programming Language :: Python :: 3
Classifier: Programming Language :: Python :: 3.12
Classifier: Programming Language :: Python :: 3 :: Only
Classifier: Topic :: Database
Classifier: Topic :: Software Development :: Libraries :: Python Modules
Requires-Dist: pydantic>=2.9.2
Requires-Dist: square-commons>=3.1.0
Requires-Dist: black>=25.12.0 ; extra == 'all'
Requires-Dist: pytest>=9.0.2 ; extra == 'all'
Requires-Dist: pytest-cov>=7.0.0 ; extra == 'all'
Requires-Dist: black>=25.12.0 ; extra == 'dev'
Requires-Dist: pytest>=9.0.2 ; extra == 'dev'
Requires-Dist: pytest-cov>=7.0.0 ; extra == 'dev'
Requires-Python: >=3.12
Project-URL: homepage, https://github.com/thepmsquare/square_database_helper
Provides-Extra: all
Provides-Extra: dev
